conviso_ast-3.0.1.data/scripts/flow_bash_completer.sh
conviso_ast-3.0.1.data/scripts/flow_fish_completer.fish
conviso_ast-3.0.1.data/scripts/flow_zsh_completer.sh
convisoappsec/__init__.py
convisoappsec/logger.py
convisoappsec/version.py
convisoappsec/common/__init__.py
convisoappsec/common/box.py
convisoappsec/common/cleaner.py
convisoappsec/common/docker.py
convisoappsec/common/exceptions.py
convisoappsec/common/git_data_parser.py
convisoappsec/common/retry_handler.py
convisoappsec/common/strings.py
convisoappsec/common/graphql/__init__.py
convisoappsec/common/graphql/error_handlers.py
convisoappsec/common/graphql/errors.py
convisoappsec/common/graphql/low_client.py
convisoappsec/flow/__init__.py
convisoappsec/flow/api.py
convisoappsec/flow/cleaner.py
convisoappsec/flow/version_control_system_adapter.py
convisoappsec/flow/graphql_api/__init__.py
convisoappsec/flow/graphql_api/beta/__init__.py
convisoappsec/flow/graphql_api/beta/client.py
convisoappsec/flow/graphql_api/beta/resources_api.py
convisoappsec/flow/graphql_api/beta/models/__init__.py
convisoappsec/flow/graphql_api/beta/models/issues/__init__.py
convisoappsec/flow/graphql_api/beta/models/issues/container.py
convisoappsec/flow/graphql_api/beta/models/issues/iac.py
convisoappsec/flow/graphql_api/beta/models/issues/normalize.py
convisoappsec/flow/graphql_api/beta/models/issues/sast.py
convisoappsec/flow/graphql_api/beta/models/issues/sca.py
convisoappsec/flow/graphql_api/beta/schemas/__init__.py
convisoappsec/flow/graphql_api/beta/schemas/mutations/__init__.py
convisoappsec/flow/graphql_api/beta/schemas/resolvers/__init__.py
convisoappsec/flow/graphql_api/v1/__init__.py
convisoappsec/flow/graphql_api/v1/client.py
convisoappsec/flow/graphql_api/v1/resources_api.py
convisoappsec/flow/graphql_api/v1/models/__init__.py
convisoappsec/flow/graphql_api/v1/models/asset.py
convisoappsec/flow/graphql_api/v1/models/issues.py
convisoappsec/flow/graphql_api/v1/models/project.py
conviso_ast-3.0.1.dist-info/METADATA
conviso_ast-3.0.1.dist-info/WHEEL
conviso_ast-3.0.1.dist-info/entry_points.txt
conviso_ast-3.0.1.dist-info/top_level.txt
conviso_ast-3.0.1.dist-info/RECORD
