Metadata-Version: 2.2
Name: conviso-ast
Version: 3.0.1
Maintainer: Conviso
Maintainer-email: development@convisoappsec.com
Project-URL: Source, https://github.com/convisoappsec/convisocli/
Requires-Python: >=3.9
Requires-Dist: GitPython==3.1.46
Requires-Dist: click==8.1.8
Requires-Dist: requests==2.32.5
Requires-Dist: urllib3==2.6.3
Requires-Dist: semantic-version==2.10.0
Requires-Dist: docker==7.1.0
Requires-Dist: PyYAML==6.0.3
Requires-Dist: click-log==0.4.0
Requires-Dist: transitions==0.9.2
Requires-Dist: jsonschema==4.25.1
Requires-Dist: giturlparse<=0.14.0
Requires-Dist: jmespath==1.0.1
Requires-Dist: setuptools==78.1.0
Dynamic: description
Dynamic: description-content-type
Dynamic: maintainer
Dynamic: maintainer-email
Dynamic: project-url
Dynamic: requires-dist
Dynamic: requires-python
